<?xml version="1.0" encoding="UTF-8" standalone="no"?>
<!DOCTYPE Root SYSTEM "roles.dtd">
<Root>
  <expRoot>
    <B132>
      <B67>
        <B73>
          <B68>
            <A42/>
          </B68>
          <B69>
            <A39/>
          </B69>
          <B70>
            <A53/>
          </B70>
          <B71>
            <A59/>
          </B71>
          <B72>
            <A63/>
          </B72>
        </B73>
      </B67>
      <B80>
        <B92>
          <B87>
            <A55/>
          </B87>
          <B88>
            <A93/>
          </B88>
          <B89>
            <A20/>
          </B89>
          <B90>
            <A56/>
          </B90>
          <B91>
            <A32/>
          </B91>
        </B92>
      </B80>
      <B93>
        <B105>
          <B100>
            <A61/>
          </B100>
          <B101>
            <A98/>
          </B101>
          <B102>
            <A82/>
          </B102>
          <B103>
            <A1/>
          </B103>
          <B104>
            <A73/>
          </B104>
        </B105>
      </B93>
      <B106>
        <B112>
          <B107>
            <A70/>
          </B107>
          <B108>
            <A79/>
          </B108>
          <B109>
            <A28/>
          </B109>
          <B110>
            <A30/>
          </B110>
          <B111>
            <A97/>
          </B111>
        </B112>
      </B106>
      <B119>
        <B131>
          <B126>
            <A43/>
          </B126>
          <B127>
            <A79/>
          </B127>
          <B128>
            <A63/>
          </B128>
          <B129>
            <A52/>
          </B129>
          <B130>
            <A67/>
          </B130>
        </B131>
      </B119>
    </B132>
  </expRoot>
</Root>
