<?xml version="1.0" encoding="UTF-8" standalone="no"?>
<!DOCTYPE Root SYSTEM "roles.dtd">
<Root>
  <expRoot>
    <B344>
      <B173>
        <B229>
          <B202>
            <B206>
              <B203>
                <A27/>
              </B203>
              <B204>
                <A2/>
              </B204>
              <B205>
                <A75/>
              </B205>
            </B206>
          </B202>
          <B211>
            <B219>
              <B216>
                <A28/>
              </B216>
              <B217>
                <A27/>
              </B217>
              <B218>
                <A78/>
              </B218>
            </B219>
          </B211>
          <B220>
            <B228>
              <B225>
                <A8/>
              </B225>
              <B226>
                <A70/>
              </B226>
              <B227>
                <A69/>
              </B227>
            </B228>
          </B220>
        </B229>
      </B173>
      <B230>
        <B286>
          <B259>
            <B267>
              <B264>
                <A14/>
              </B264>
              <B265>
                <A14/>
              </B265>
              <B266>
                <A82/>
              </B266>
            </B267>
          </B259>
          <B268>
            <B276>
              <B273>
                <A23/>
              </B273>
              <B274>
                <A9/>
              </B274>
              <B275>
                <A19/>
              </B275>
            </B276>
          </B268>
          <B277>
            <B285>
              <B282>
                <A3/>
              </B282>
              <B283>
                <A7/>
              </B283>
              <B284>
                <A70/>
              </B284>
            </B285>
          </B277>
        </B286>
      </B230>
      <B287>
        <B315>
          <B288>
            <B296>
              <B293>
                <A43/>
              </B293>
              <B294>
                <A9/>
              </B294>
              <B295>
                <A54/>
              </B295>
            </B296>
          </B288>
          <B297>
            <B301>
              <B298>
                <A2/>
              </B298>
              <B299>
                <A46/>
              </B299>
              <B300>
                <A96/>
              </B300>
            </B301>
          </B297>
          <B306>
            <B314>
              <B311>
                <A95/>
              </B311>
              <B312>
                <A72/>
              </B312>
              <B313>
                <A14/>
              </B313>
            </B314>
          </B306>
        </B315>
      </B287>
    </B344>
  </expRoot>
</Root>
