<?xml version='1.0' encoding='ISO-8859-1'?>
<Observations><Observation id="A34" /><Observation id="A52" /><Observation id="A82" /><Observation id="A35" /><Observation id="A96" /><Observation id="A24" /><Observation id="A70" /><Observation id="A10" /><Observation id="A52" /><Observation id="A60" /><Observation id="A36" /><Observation id="A77" /><Observation id="A3" /><Observation id="A93" /><Observation id="A19" /><Observation id="A21" /><Observation id="A83" /><Observation id="A25" /><Observation id="A54" /><Observation id="A27" /><Observation id="A76" /><Observation id="A74" /><Observation id="A47" /><Observation id="A7" /><Observation id="A57" /></Observations>